{
  "_fv": 57,
  "_type": "tag",
  "definition": {
    "type": "Blocks",
    "items": [],
    "blocks": [
      {
        "value": "CUSTOM:RustRecuperacoonCore"
      },
      {
        "value": "CUSTOM:BronzeRecuperacoonCore"
      },
      {
        "value": "CUSTOM:GoldRecuperacoonCore"
      },
      {
        "value": "CUSTOM:LimeRecuperacoonCore"
      },
      {
        "value": "CUSTOM:OliveRecuperacoonCore"
      },
      {
        "value": "CUSTOM:JadeRecuperacoonCore"
      },
      {
        "value": "CUSTOM:TealRecuperacoonCore"
      },
      {
        "value": "CUSTOM:CobaltRecuperacoonCore"
      },
      {
        "value": "CUSTOM:IndigoRecuperacoonCore"
      },
      {
        "value": "CUSTOM:PurpleRecuperacoonCore"
      },
      {
        "value": "CUSTOM:VioletRecuperacoonCore"
      },
      {
        "value": "CUSTOM:FuchsiaRecuperacoonCore"
      }
    ],
    "functions": [],
    "entities": [],
    "biomes": [],
    "damageTypes": [],
    "name": "recuperacoon_core",
    "namespace": "mod"
  }
}